shared_redis/__init__.py
shared_redis/client.py
shared_redis/hash_algorithm.py
shared_redis/user_demo.py
src/__init__.py
src/hash_algorithm.py
src/redis_sharding_client.py
src/user_demo.py
pyshared_redis-0.0.2.dist-info/METADATA
pyshared_redis-0.0.2.dist-info/WHEEL
pyshared_redis-0.0.2.dist-info/top_level.txt
pyshared_redis-0.0.2.dist-info/RECORD
