Metadata-Version: 2.1
Name: pyshared-redis
Version: 0.0.2
Summary: python shared redis client
Home-page: https://github.com/gantang001/pyshared-redis
Author: hanshuo
Author-email: 837145493@qq.com
Maintainer: hanshuo
Maintainer-email: 837145493@qq.com
License: BSD License
Platform: all
Classifier: Development Status :: 4 - Beta
Classifier: Operating System :: OS Independent
Classifier: Intended Audience :: Developers
Classifier: License :: OSI Approved :: BSD License
Classifier: Programming Language :: Python
Classifier: Programming Language :: Python :: Implementation
Classifier: Programming Language :: Python :: 2
Classifier: Programming Language :: Python :: 2.7
Classifier: Topic :: Software Development :: Libraries
Requires-Dist: redis (>=2.10.6)
